URISC-Verilog/Alu.v
module ALU (
    input  wire [15:0] bus_in,  // Operando B (Vem do Barramento)
    input  wire [15:0] r_in,    // Operando A (Vem do Registrador R)
    input  wire comp,           // Sinal de Controle: 0=Soma, 1=Subtração
    output wire [15:0] result,  // Resultado
    output wire flag_n,         // Flag Negativo (Bit mais significativo)
    output wire flag_z          // Flag Zero (Nor de todos os bits)
);

    // --- Lógica do Complemento de 2 ---
    // Para subtrair A de B (B - A), o hardware faz: B + (~A) + 1
    
    // 1. Inversão (NOT):
    // Se o sinal 'comp' estiver ativo, invertemos todos os bits de A.
    wire [15:0] r_ajustado;
    assign r_ajustado = (comp) ? ~r_in : r_in;

    // 2. Somador (Adder):
    // Somamos B + A_invertido.
    // O trunfo: O sinal 'comp' (que é 1 na subtração) é somado na entrada de Carry In.
    // Isso completa a lógica do "+1" do Complemento de 2.
    assign result = bus_in + r_ajustado + comp;

    // 3. Geração de Flags:
    // Estas flags são geradas combinacionalmente (instantaneamente).
    assign flag_z = (result == 16'd0); 
    assign flag_n = result[15]; // Em complemento de 2, o bit 15 é o sinal.

endmodule

URISC/memory.v
module Memory(
    input  wire clk,
    input  wire [15:0] addr,     // Endereço de 16 bits (Vem do MAR)
    input  wire [15:0] data_in,  // 16 bits de dados (Vem do MDR)
    input  wire write_en,
    input  wire read_en,
    output reg  [15:0] data_out  //16 bits de dados (Vai para o MDR)
);


    reg [15:0] ram_block [0:(1<<10)-1];

    // 2. Escrita
    always @(posedge clk) begin
        if (write_en) begin

            ram_block[addr[9:0]] <= data_in;
        end
    end

    // 3. Leitura
    always @(*) begin
        if (read_en)
            data_out = ram_block[addr[9:0]];
        else
            data_out = 16'd0; // Zera saída 
    end

    // 4. Inicialização
    initial begin
        $readmemh("programa.hex", ram_block);
    end

endmodule

URISC-Verilog/Register.v
module Register #(
    parameter WIDTH = 16,
    parameter HAS_INC = 0 // 0 = Registrador Comum, 1 = Registrador com Soma
)(
    input  wire clk,
    input  wire reset,
    input  wire load,       // Carga paralela (ex: Pulo/Branch)
    input  wire inc,
    input  wire [WIDTH-1:0] data_in,
    output reg  [WIDTH-1:0] data_out
);

    always @(posedge clk or posedge reset) begin
        if (reset) begin
            data_out <= 0;
        end else if (load) begin
            data_out <= data_in;
        end else if (HAS_INC && inc) begin
            // Só compila essa lógica se HAS_INC = 1
            data_out <= data_out + 1;
        end
    end

endmodule

URISC/Datapath.v
module Datapath (
    input  wire clk,
    input  wire reset,

    // Sinais de Controle
    input  wire pc_in, pc_out,
    input  wire pc_inc,
    input  wire r_in,
    input  wire mar_in,
    input  wire mdr_in, mdr_out,
    input  wire read_mem, write_mem,
    input  wire comp_alu,
    input  wire save_flags, // <--- NOVO SINAL (Importante!)

    // Saídas para a Unidade de Controle
    output reg flag_z,      // <--- Virou REG (Memória)
    output reg flag_n       // <--- Virou REG (Memória)
);

    wire [15:0] bus;
    wire [15:0] pc_val;
    wire [15:0] r_val;
    wire [15:0] mar_val;
    wire [15:0] mdr_val_out;
    wire [15:0] mem_data_out;
    wire [15:0] alu_result;
    wire [15:0] mdr_data_in;

    // Fios temporários para a saída instantânea da ALU
    wire alu_z_instantaneo;
    wire alu_n_instantaneo;

    assign bus = (pc_out)  ? pc_val :
                 (mdr_out) ? mdr_val_out :
                 16'd0;

    // --- Lógica de Salvamento das Flags ---
    always @(posedge clk or posedge reset) begin
        if (reset) begin
            flag_z <= 0;
            flag_n <= 0;
        end else if (save_flags) begin
            // Tira uma "foto" das flags neste exato momento
            flag_z <= alu_z_instantaneo;
            flag_n <= alu_n_instantaneo;
        end
    end

    // --- Componentes ---
    Register #(.WIDTH(16), .HAS_INC(1)) PC (.clk(clk), .reset(reset), .load(pc_in), .inc(pc_inc), .data_in(bus), .data_out(pc_val));
    Register #(.WIDTH(16), .HAS_INC(0)) R (.clk(clk), .reset(reset), .load(r_in), .inc(1'b0), .data_in(bus), .data_out(r_val));
    Register #(.WIDTH(16), .HAS_INC(0)) MAR (.clk(clk), .reset(reset), .load(mar_in), .inc(1'b0), .data_in(bus), .data_out(mar_val));
    
    assign mdr_data_in = (read_mem) ? mem_data_out : (comp_alu) ? alu_result : bus;
    wire mdr_load_enable = mdr_in | read_mem; 
    Register #(.WIDTH(16)) MDR (.clk(clk), .reset(reset), .load(mdr_load_enable), .data_in(mdr_data_in), .data_out(mdr_val_out));
    
    Memory RAM (.clk(clk), .addr(mar_val), .data_in(mdr_val_out), .write_en(write_mem), .read_en(read_mem), .data_out(mem_data_out));

    // --- ALU Conectada aos Fios Temporários ---
    ALU alu_instance (
        .bus_in(bus),
        .r_in(r_val),
        .comp(comp_alu),
        .result(alu_result),
        .flag_z(alu_z_instantaneo), // Conecta aqui
        .flag_n(alu_n_instantaneo)  // Conecta aqui
    );

endmodule

URISC-Verilog/controlUnit.v
module ControlUnit (
    input  wire clk,
    input  wire reset,
    input  wire flag_z,
    input  wire flag_n,

    output reg pc_out, pc_in, pc_inc,
    output reg r_in,
    output reg mar_in,
    output reg mdr_in, mdr_out,
    output reg read_mem, write_mem,
    output reg comp_alu,
    output reg save_flags 
);

    integer estado_atual;

    // --- Máquina de Estados Finitos (FSM) ---
    // Define a coreografia dos dados a cada pulso de clock.
    always @(posedge clk or posedge reset) begin
        if (reset) estado_atual <= 0;
        else begin
            case (estado_atual)
                0: estado_atual <= 1; // Start

                // == FASE 1: BUSCA DO PRIMEIRO OPERANDO (A) ==
                // O URISC usa Indireção: O código contém o ENDEREÇO de A, não o valor.
                // 1-3: Buscamos o ponteiro "A" na memória de programa.
                // 4-5: Usamos esse ponteiro para buscar o DADO real na memória de dados.
                1: estado_atual <= 2; 2: estado_atual <= 3;
                3: estado_atual <= 4; 4: estado_atual <= 5; 5: estado_atual <= 6;

                // == FASE 2: BUSCA DO SEGUNDO OPERANDO (B) ==
                // Mesmo processo: Busca Ponteiro -> Configura Endereço -> Busca Dado.
                // Ao final (Estado 9), o MAR (Registrador de Endereço) aponta para B.
                // Isso é crucial para gravarmos o resultado de volta em B depois.
                6: estado_atual <= 7; 7: estado_atual <= 8; 8: estado_atual <= 9;
                9: estado_atual <= 10;

                // == FASE 3: EXECUÇÃO (ALU) ==
                // Realiza a subtração B - A.
                10: estado_atual <= 11;

                // == FASE 4: WRITEBACK (Escrita) ==
                // Salva o resultado da subtração na memória (sobrescreve B).
                11: estado_atual <= 12;

                // == FASE 5: BUSCA DO DESTINO (C) E BRANCH ==
                // Busca o terceiro operando (C), que é o endereço de pulo.
                // Decide se altera o PC (Pulo) ou apenas incrementa (Próxima instrução).
                12: estado_atual <= 13;
                13: estado_atual <= 14; 
                14: estado_atual <= 1; // Reinicia o ciclo (Loop Infinito)
                default: estado_atual <= 0;
            endcase
        end
    end

    // --- Decodificação dos Sinais de Controle ---
    // Em cada estado, definimos quais "chaves" (tristates) do hardware ligar.
    always @(*) begin
        // Reset dos sinais (Segurança)
        pc_out = 0; pc_in = 0; pc_inc = 0; r_in = 0; mar_in = 0;
        mdr_in = 0; mdr_out = 0; read_mem = 0; write_mem = 0; comp_alu = 0;
        save_flags = 0; 

        case (estado_atual)
            // Lógica de Movimentação de Dados (Busca Indireta)
            1: begin pc_out = 1; mar_in = 1; read_mem = 1; end // PC -> MAR
            2: begin read_mem = 1; end                         // Espera Memória
            3: begin mdr_out = 1; mar_in = 1; end              // Ponteiro A -> MAR
            4: begin read_mem = 1; end                         // Lê Valor A
            5: begin mdr_out = 1; r_in = 1; pc_inc = 1; end    // Valor A -> Reg R (Guarda A)
            
            6: begin pc_out = 1; mar_in = 1; read_mem = 1; end // PC -> MAR (Buscando B)
            7: begin read_mem = 1; end
            8: begin mdr_out = 1; mar_in = 1; end              // Ponteiro B -> MAR
            9: begin read_mem = 1; end                         // Lê Valor B

            // --- PONTO CRÍTICO: A OPERAÇÃO ---
            10: begin
                mdr_out = 1;   // Coloca Valor B no Barramento
                comp_alu = 1;  // Ativa Subtração na ALU (Bus - R)
                mdr_in = 1;    // O resultado volta para o MDR
                read_mem = 0;  // Desliga memória para evitar conflito no barramento
                
                // Salva o estado da ALU (Zero/Negativo) neste exato momento.
                // Se não salvarmos aqui, perderemos essa informação no próximo clock.
                save_flags = 1; 
            end

            // Escrita na Memória
            11: begin write_mem = 1; pc_inc = 1; end // Grava MDR na pos B (MAR ainda aponta p/ B)

            // Preparação para o Pulo
            12: begin pc_out = 1; mar_in = 1; read_mem = 1; end // PC -> MAR (Endereço C)
            13: begin read_mem = 1; end // Lê C

            // --- PONTO CRÍTICO: DECISÃO (BRANCH) ---
            14: begin
                // Consulta as Flags que foram salvas no Estado 10.
                if (flag_z || flag_n) begin 
                    mdr_out = 1; // Coloca endereço C no barramento
                    pc_in = 1;   // Carga Paralela no PC (JUMP)
                end else begin
                    pc_inc = 1;  // Apenas avança PC (PC + 1)
                end
            end
        endcase
    end
endmodule

URISC/URISC.v
module Processor (
    input wire clk,
    input wire reset
);
    // --- Barramento de Controle (O "Sistema Nervoso") ---
    // Estes fios transportam os comandos da Unidade de Controle para ativar/desativar
    // componentes específicos no Datapath (ex: abrir a porta do PC, gravar na Memória).
    wire ctrl_pc_out, ctrl_pc_in, ctrl_pc_inc;
    wire ctrl_r_in, ctrl_mar_in;
    wire ctrl_mdr_in, ctrl_mdr_out;
    wire ctrl_read_mem, ctrl_write_mem;
    wire ctrl_comp_alu;
    
    // Sinal crítico para arquiteturas sequenciais:
    // Como a decisão de pulo (Branch) ocorre ciclos DEPOIS da subtração,
    // precisamos congelar (salvar) o resultado das Flags Z e N.
    wire ctrl_save_flags; 

    // --- Sinais de Status (Feedback) ---
    // O Datapath informa ao Controle o resultado da última operação matemática.
    wire status_z;
    wire status_n;

    // --- 1. Instância do Cérebro (Unidade de Controle) ---
    // Responsável por orquestrar a sequência de micro-operações.
    // Em URISC, como só há uma instrução, não há "Decodificação de Opcode",
    // apenas uma máquina de estados fixa.
    ControlUnit controle (
        .clk(clk),
        .reset(reset),
        // Entradas: Toma decisões baseadas no estado atual do processador (Flags)
        .flag_z(status_z),
        .flag_n(status_n),
        // Saídas: Comanda os componentes
        .pc_out(ctrl_pc_out), .pc_in(ctrl_pc_in), .pc_inc(ctrl_pc_inc),
        .r_in(ctrl_r_in), .mar_in(ctrl_mar_in),
        .mdr_in(ctrl_mdr_in), .mdr_out(ctrl_mdr_out),
        .read_mem(ctrl_read_mem), .write_mem(ctrl_write_mem),
        .comp_alu(ctrl_comp_alu),
        
        .save_flags(ctrl_save_flags) 
    );

    // --- 2. Instância do Corpo (Datapath) ---
    // Onde os dados realmente fluem e são processados.
    // Contém os Registradores, a ALU e a Memória.
    Datapath caminho (
        .clk(clk),
        .reset(reset),
        // Recebe ordens cegas do Controle
        .pc_out(ctrl_pc_out), .pc_in(ctrl_pc_in), .pc_inc(ctrl_pc_inc),
        .r_in(ctrl_r_in), .mar_in(ctrl_mar_in),
        .mdr_in(ctrl_mdr_in), .mdr_out(ctrl_mdr_out),
        .read_mem(ctrl_read_mem), .write_mem(ctrl_write_mem),
        .comp_alu(ctrl_comp_alu),
        
        .save_flags(ctrl_save_flags),

        // Envia o status do processamento
        .flag_z(status_z),
        .flag_n(status_n)
    );
endmodule

URISC/Testbench.v
`timescale 1ns / 1ps

module Testbench;

    // 1. Sinais para conectar no Processador
    reg clk;
    reg reset;

    // 2. Instância do Processador (UUT - Unit Under Test)
    Processor uut (
        .clk(clk),
        .reset(reset)
    );

    // 3. Geração de Clock (Periodo = 10ns)
    always #5 clk = ~clk;

    // 4. Bloco de Teste Principal
    initial begin
        // Configuração Inicial (Gera arquivo de onda para visualizar depois)
        $dumpfile("urisc_wave.vcd");
        $dumpvars(0, Testbench);

        // Inicializa sinais
        clk = 0;
        reset = 1;

        // Print de Cabeçalho
        $display("-------------------------------------------------------------");
        $display("Tempo | PC  | Estado | MAR  | MDR  | R (A)| Mem[9] (Var B)");
        $display("-------------------------------------------------------------");

        // Solta o Reset após um tempo
        #10 reset = 0;

        #2000; 
        
        $display("-------------------------------------------------------------");
        $display("FIM DA SIMULACAO");
        $finish;
    end

    // 5. Monitoramento (Imprime no console a cada borda de subida do clock)
    // Acessamos os sinais internos usando o ponto (.) ex: uut.controle.estado_atual
    always @(posedge clk) begin
        if (!reset) begin
            $display("%4t  | %3d |   %2d   | %4x | %4x | %4x |      %4x", 
                $time, 
                uut.caminho.PC.data_out,       // Valor do PC
                uut.controle.estado_atual,     // Estado da FSM
                uut.caminho.MAR.data_out,      // Valor do MAR
                uut.caminho.MDR.data_out,      // Valor do MDR
                uut.caminho.R.data_out,        // Valor de R (Operando A)
                uut.caminho.RAM.ram_block[9]  // Espionando a memória diretamente (Endereço 11)
            );
        end
    end

endmodule

URISC/urisc_wave.vcd
$date
	Sun Feb 08 17:53:09 2026
$end
$version
	Icarus Verilog
$end
$timescale
	1ps
$end
$scope module Testbench $end
$var reg 1 ! clk $end
$var reg 1 " reset $end
$scope module uut $end
$var wire 1 ! clk $end
$var wire 1 " reset $end
$var wire 1 # status_z $end
$var wire 1 $ status_n $end
$var wire 1 % ctrl_write_mem $end
$var wire 1 & ctrl_save_flags $end
$var wire 1 ' ctrl_read_mem $end
$var wire 1 ( ctrl_r_in $end
$var wire 1 ) ctrl_pc_out $end
$var wire 1 * ctrl_pc_inc $end
$var wire 1 + ctrl_pc_in $end
$var wire 1 , ctrl_mdr_out $end
$var wire 1 - ctrl_mdr_in $end
$var wire 1 . ctrl_mar_in $end
$var wire 1 / ctrl_comp_alu $end
$scope module caminho $end
$var wire 1 ! clk $end
$var wire 1 0 mdr_load_enable $end
$var wire 1 " reset $end
$var wire 1 % write_mem $end
$var wire 1 & save_flags $end
$var wire 1 ' read_mem $end
$var wire 16 1 r_val [15:0] $end
$var wire 1 ( r_in $end
$var wire 16 2 pc_val [15:0] $end
$var wire 1 ) pc_out $end
$var wire 1 * pc_inc $end
$var wire 1 + pc_in $end
$var wire 16 3 mem_data_out [15:0] $end
$var wire 16 4 mdr_val_out [15:0] $end
$var wire 1 , mdr_out $end
$var wire 1 - mdr_in $end
$var wire 16 5 mdr_data_in [15:0] $end
$var wire 16 6 mar_val [15:0] $end
$var wire 1 . mar_in $end
$var wire 1 / comp_alu $end
$var wire 16 7 bus [15:0] $end
$var wire 1 8 alu_z_instantaneo $end
$var wire 16 9 alu_result [15:0] $end
$var wire 1 : alu_n_instantaneo $end
$var reg 1 $ flag_n $end
$var reg 1 # flag_z $end
$scope module MAR $end
$var wire 1 ! clk $end
$var wire 16 ; data_in [15:0] $end
$var wire 1 < inc $end
$var wire 1 " reset $end
$var wire 1 . load $end
$var parameter 32 = HAS_INC $end
$var parameter 32 > WIDTH $end
$var reg 16 ? data_out [15:0] $end
$upscope $end
$scope module MDR $end
$var wire 1 ! clk $end
$var wire 16 @ data_in [15:0] $end
$var wire 1 A inc $end
$var wire 1 0 load $end
$var wire 1 " reset $end
$var parameter 32 B HAS_INC $end
$var parameter 32 C WIDTH $end
$var reg 16 D data_out [15:0] $end
$upscope $end
$scope module PC $end
$var wire 1 ! clk $end
$var wire 16 E data_in [15:0] $end
$var wire 1 " reset $end
$var wire 1 + load $end
$var wire 1 * inc $end
$var parameter 32 F HAS_INC $end
$var parameter 32 G WIDTH $end
$var reg 16 H data_out [15:0] $end
$upscope $end
$scope module R $end
$var wire 1 ! clk $end
$var wire 16 I data_in [15:0] $end
$var wire 1 J inc $end
$var wire 1 " reset $end
$var wire 1 ( load $end
$var parameter 32 K HAS_INC $end
$var parameter 32 L WIDTH $end
$var reg 16 M data_out [15:0] $end
$upscope $end
$scope module RAM $end
$var wire 16 N addr [15:0] $end
$var wire 1 ! clk $end
$var wire 16 O data_in [15:0] $end
$var wire 1 % write_en $end
$var wire 1 ' read_en $end
$var reg 16 P data_out [15:0] $end
$upscope $end
$scope module alu_instance $end
$var wire 16 Q bus_in [15:0] $end
$var wire 16 R r_in [15:0] $end
$var wire 16 S result [15:0] $end
$var wire 16 T r_ajustado [15:0] $end
$var wire 1 8 flag_z $end
$var wire 1 : flag_n $end
$var wire 1 / comp $end
$upscope $end
$upscope $end
$scope module controle $end
$var wire 1 ! clk $end
$var wire 1 $ flag_n $end
$var wire 1 # flag_z $end
$var wire 1 " reset $end
$var reg 1 / comp_alu $end
$var reg 1 . mar_in $end
$var reg 1 - mdr_in $end
$var reg 1 , mdr_out $end
$var reg 1 + pc_in $end
$var reg 1 * pc_inc $end
$var reg 1 ) pc_out $end
$var reg 1 ( r_in $end
$var reg 1 ' read_mem $end
$var reg 1 & save_flags $end
$var reg 1 % write_mem $end
$var integer 32 U estado_atual [31:0] $end
$upscope $end
$upscope $end
$upscope $end
$enddefinitions $end
$comment Show the parameter values. $end
$dumpall
b10000 L
b0 K
b10000 G
b1 F
b10000 C
b0 B
b10000 >
b0 =
$end
#0
$dumpvars
b0 U
b0 T
b0 S
b0 R
b0 Q
b0 P
b0 O
b0 N
b0 M
0J
b0 I
b0 H
b0 E
b0 D
zA
b0 @
b0 ?
0<
b0 ;
0:
b0 9
18
b0 7
b0 6
b0 5
b0 4
b0 3
b0 2
b0 1
00
0/
0.
0-
0,
0+
0*
0)
0(
0'
0&
0%
0$
0#
1"
0!
$end
#5000
1!
#10000
0!
0"
#15000
b1010 5
b1010 @
10
b1010 3
b1010 P
1'
1.
1)
b1 U
1!
#20000
0!
#25000
1'
0.
0)
b1010 4
b1010 D
b1010 O
b10 U
1!
#30000
0!
#35000
08
b1010 9
b1010 S
b1010 7
b1010 ;
b1010 E
b1010 I
b1010 Q
b1010 5
b1010 @
00
b0 3
b0 P
1.
1,
0'
b11 U
1!
#40000
0!
#45000
18
b0 9
b0 S
b0 7
b0 ;
b0 E
b0 I
b0 Q
b1 5
b1 @
10
b1 3
b1 P
1'
0,
0.
b1010 6
b1010 ?
b1010 N
b100 U
1!
#50000
0!
#55000
08
b1 9
b1 S
b1 7
b1 ;
b1 E
b1 I
b1 Q
b1 5
b1 @
00
b0 3
b0 P
1*
1(
1,
0'
b101 U
b1 4
b1 D
b1 O
1!
#60000
0!
#65000
10
b1 3
b1 P
b10 9
b10 S
b1 T
1'
1.
1)
0,
0(
0*
b1 1
b1 M
b1 R
b1 2
b1 H
b110 U
1!
#70000
0!
#75000
b1 9
b1 S
b0 7
b0 ;
b0 E
b0 I
b0 Q
b1001 5
b1001 @
1'
0.
0)
b1001 3
b1001 P
b111 U
b1 6
b1 ?
b1 N
1!
#80000
0!
#85000
b1010 9
b1010 S
b1001 7
b1001 ;
b1001 E
b1001 I
b1001 Q
b1001 5
b1001 @
00
b0 3
b0 P
1.
1,
0'
b1001 4
b1001 D
b1001 O
b1000 U
1!
#90000
0!
#95000
b1 9
b1 S
b0 7
b0 ;
b0 E
b0 I
b0 Q
b111 5
b111 @
10
b111 3
b111 P
1'
0,
0.
b1001 U
b1001 6
b1001 ?
b1001 N
1!
#100000
0!
#105000
b111 7
b111 ;
b111 E
b111 I
b111 Q
b1111111111111110 T
b110 5
b110 @
b0 3
b0 P
1&
1-
b110 9
b110 S
1/
1,
0'
b111 4
b111 D
b111 O
b1010 U
1!
#110000
0!
#115000
b0 5
b0 @
b1 T
00
b0 7
b0 ;
b0 E
b0 I
b0 Q
1*
1%
0&
b1 9
b1 S
0/
0,
0-
b1011 U
b110 4
b110 D
b110 O
1!
#120000
0!
#125000
b110 5
b110 @
10
b110 3
b110 P
b11 9
b11 S
b10 7
b10 ;
b10 E
b10 I
b10 Q
1'
1.
1)
0%
0*
b10 2
b10 H
b1100 U
1!
#130000
0!
#135000
b1 9
b1 S
b0 7
b0 ;
b0 E
b0 I
b0 Q
1'
0.
0)
b1101 U
b10 6
b10 ?
b10 N
1!
#140000
0!
#145000
b0 5
b0 @
00
b0 3
b0 P
1*
0'
b1110 U
1!
#150000
0!
#155000
b110 5
b110 @
10
b110 3
b110 P
b100 9
b100 S
b11 7
b11 ;
b11 E
b11 I
b11 Q
1'
1.
1)
0*
b1 U
b11 2
b11 H
1!
#160000
0!
#165000
b1011 5
b1011 @
b1 9
b1 S
b0 7
b0 ;
b0 E
b0 I
b0 Q
b1011 3
b1011 P
1'
0.
0)
b11 6
b11 ?
b11 N
b10 U
1!
#170000
0!
#175000
b1100 9
b1100 S
b1011 7
b1011 ;
b1011 E
b1011 I
b1011 Q
b1011 5
b1011 @
00
b0 3
b0 P
1.
1,
0'
b11 U
b1011 4
b1011 D
b1011 O
1!
#180000
0!
#185000
b1 9
b1 S
b0 7
b0 ;
b0 E
b0 I
b0 Q
b0 5
b0 @
10
1'
0,
0.
b1011 6
b1011 ?
b1011 N
b100 U
1!
#190000
0!
#195000
00
1*
1(
1,
0'
b101 U
b0 4
b0 D
b0 O
1!
#200000
0!
#205000
10
b100 7
b100 ;
b100 E
b100 I
b100 Q
08
b100 9
b100 S
b0 T
1'
1.
1)
0,
0(
0*
b0 1
b0 M
b0 R
b100 2
b100 H
b110 U
1!
#210000
0!
#215000
18
b0 9
b0 S
b0 7
b0 ;
b0 E
b0 I
b0 Q
b1011 5
b1011 @
1'
0.
0)
b1011 3
b1011 P
b111 U
b100 6
b100 ?
b100 N
1!
#220000
0!
#225000
08
b1011 9
b1011 S
b1011 7
b1011 ;
b1011 E
b1011 I
b1011 Q
b1011 5
b1011 @
00
b0 3
b0 P
1.
1,
0'
b1011 4
b1011 D
b1011 O
b1000 U
1!
#230000
0!
#235000
18
b0 9
b0 S
b0 7
b0 ;
b0 E
b0 I
b0 Q
b0 5
b0 @
10
1'
0,
0.
b1001 U
b1011 6
b1011 ?
b1011 N
1!
#240000
0!
#245000
b0 5
b0 @
b1111111111111111 T
1&
1-
18
b0 9
b0 S
1/
1,
0'
b0 4
b0 D
b0 O
b1010 U
1!
#250000
0!
#255000
b0 T
00
1*
1%
0&
18
b0 9
b0 S
0/
0,
0-
b1011 U
1#
1!
#260000
0!
#265000
10
08
b101 9
b101 S
b101 7
b101 ;
b101 E
b101 I
b101 Q
1'
1.
1)
0%
0*
b101 2
b101 H
b1100 U
1!
#270000
0!
#275000
18
b0 9
b0 S
b0 7
b0 ;
b0 E
b0 I
b0 Q
1'
0.
0)
b1101 U
b101 6
b101 ?
b101 N
1!
#280000
0!
#285000
00
1+
1,
0'
b1110 U
1!
#290000
0!
#295000
10
1'
1.
1)
0,
0+
b1 U
b0 2
b0 H
1!
#300000
0!
#305000
b1010 5
b1010 @
b1010 3
b1010 P
1'
0.
0)
b0 6
b0 ?
b0 N
b10 U
1!
#310000
0!
#315000
08
b1010 9
b1010 S
b1010 7
b1010 ;
b1010 E
b1010 I
b1010 Q
b1010 5
b1010 @
00
b0 3
b0 P
1.
1,
0'
b11 U
b1010 4
b1010 D
b1010 O
1!
#320000
0!
#325000
18
b0 9
b0 S
b0 7
b0 ;
b0 E
b0 I
b0 Q
b1 5
b1 @
10
b1 3
b1 P
1'
0,
0.
b1010 6
b1010 ?
b1010 N
b100 U
1!
#330000
0!
#335000
08
b1 9
b1 S
b1 7
b1 ;
b1 E
b1 I
b1 Q
b1 5
b1 @
00
b0 3
b0 P
1*
1(
1,
0'
b101 U
b1 4
b1 D
b1 O
1!
#340000
0!
#345000
10
b1 3
b1 P
b10 9
b10 S
b1 T
1'
1.
1)
0,
0(
0*
b1 1
b1 M
b1 R
b1 2
b1 H
b110 U
1!
#350000
0!
#355000
b1 9
b1 S
b0 7
b0 ;
b0 E
b0 I
b0 Q
b1001 5
b1001 @
1'
0.
0)
b1001 3
b1001 P
b111 U
b1 6
b1 ?
b1 N
1!
#360000
0!
#365000
b1010 9
b1010 S
b1001 7
b1001 ;
b1001 E
b1001 I
b1001 Q
b1001 5
b1001 @
00
b0 3
b0 P
1.
1,
0'
b1001 4
b1001 D
b1001 O
b1000 U
1!
#370000
0!
#375000
b1 9
b1 S
b0 7
b0 ;
b0 E
b0 I
b0 Q
b110 5
b110 @
10
b110 3
b110 P
1'
0,
0.
b1001 U
b1001 6
b1001 ?
b1001 N
1!
#380000
0!
#385000
b110 7
b110 ;
b110 E
b110 I
b110 Q
b1111111111111110 T
b101 5
b101 @
b0 3
b0 P
1&
1-
b101 9
b101 S
1/
1,
0'
b110 4
b110 D
b110 O
b1010 U
1!
#390000
0!
#395000
b0 5
b0 @
b0 7
b0 ;
b0 E
b0 I
b0 Q
b1 T
00
1*
1%
0&
b1 9
b1 S
0/
0,
0-
b1011 U
b101 4
b101 D
b101 O
0#
1!
#400000
0!
#405000
b101 5
b101 @
10
b101 3
b101 P
b11 9
b11 S
b10 7
b10 ;
b10 E
b10 I
b10 Q
1'
1.
1)
0%
0*
b10 2
b10 H
b1100 U
1!
#410000
0!
#415000
b1 9
b1 S
b0 7
b0 ;
b0 E
b0 I
b0 Q
b110 5
b110 @
1'
0.
0)
b110 3
b110 P
b1101 U
b10 6
b10 ?
b10 N
1!
#420000
0!
#425000
b0 5
b0 @
00
b0 3
b0 P
1*
0'
b110 4
b110 D
b110 O
b1110 U
1!
#430000
0!
#435000
b110 5
b110 @
10
b110 3
b110 P
b100 9
b100 S
b11 7
b11 ;
b11 E
b11 I
b11 Q
1'
1.
1)
0*
b1 U
b11 2
b11 H
1!
#440000
0!
#445000
b1011 5
b1011 @
b1 9
b1 S
b0 7
b0 ;
b0 E
b0 I
b0 Q
b1011 3
b1011 P
1'
0.
0)
b11 6
b11 ?
b11 N
b10 U
1!
#450000
0!
#455000
b1100 9
b1100 S
b1011 7
b1011 ;
b1011 E
b1011 I
b1011 Q
b1011 5
b1011 @
00
b0 3
b0 P
1.
1,
0'
b11 U
b1011 4
b1011 D
b1011 O
1!
#460000
0!
#465000
b1 9
b1 S
b0 7
b0 ;
b0 E
b0 I
b0 Q
b0 5
b0 @
10
1'
0,
0.
b1011 6
b1011 ?
b1011 N
b100 U
1!
#470000
0!
#475000
00
1*
1(
1,
0'
b101 U
b0 4
b0 D
b0 O
1!
#480000
0!
#485000
10
b100 7
b100 ;
b100 E
b100 I
b100 Q
08
b100 9
b100 S
b0 T
1'
1.
1)
0,
0(
0*
b0 1
b0 M
b0 R
b100 2
b100 H
b110 U
1!
#490000
0!
#495000
18
b0 9
b0 S
b0 7
b0 ;
b0 E
b0 I
b0 Q
b1011 5
b1011 @
1'
0.
0)
b1011 3
b1011 P
b111 U
b100 6
b100 ?
b100 N
1!
#500000
0!
#505000
08
b1011 9
b1011 S
b1011 7
b1011 ;
b1011 E
b1011 I
b1011 Q
b1011 5
b1011 @
00
b0 3
b0 P
1.
1,
0'
b1011 4
b1011 D
b1011 O
b1000 U
1!
#510000
0!
#515000
18
b0 9
b0 S
b0 7
b0 ;
b0 E
b0 I
b0 Q
b0 5
b0 @
10
1'
0,
0.
b1001 U
b1011 6
b1011 ?
b1011 N
1!
#520000
0!
#525000
b0 5
b0 @
b1111111111111111 T
1&
1-
18
b0 9
b0 S
1/
1,
0'
b0 4
b0 D
b0 O
b1010 U
1!
#530000
0!
#535000
b0 T
00
1*
1%
0&
18
b0 9
b0 S
0/
0,
0-
b1011 U
1#
1!
#540000
0!
#545000
10
08
b101 9
b101 S
b101 7
b101 ;
b101 E
b101 I
b101 Q
1'
1.
1)
0%
0*
b101 2
b101 H
b1100 U
1!
#550000
0!
#555000
18
b0 9
b0 S
b0 7
b0 ;
b0 E
b0 I
b0 Q
1'
0.
0)
b1101 U
b101 6
b101 ?
b101 N
1!
#560000
0!
#565000
00
1+
1,
0'
b1110 U
1!
#570000
0!
#575000
10
1'
1.
1)
0,
0+
b1 U
b0 2
b0 H
1!
#580000
0!
#585000
b1010 5
b1010 @
b1010 3
b1010 P
1'
0.
0)
b0 6
b0 ?
b0 N
b10 U
1!
#590000
0!
#595000
08
b1010 9
b1010 S
b1010 7
b1010 ;
b1010 E
b1010 I
b1010 Q
b1010 5
b1010 @
00
b0 3
b0 P
1.
1,
0'
b11 U
b1010 4
b1010 D
b1010 O
1!
#600000
0!
#605000
18
b0 9
b0 S
b0 7
b0 ;
b0 E
b0 I
b0 Q
b1 5
b1 @
10
b1 3
b1 P
1'
0,
0.
b1010 6
b1010 ?
b1010 N
b100 U
1!
#610000
0!
#615000
08
b1 9
b1 S
b1 7
b1 ;
b1 E
b1 I
b1 Q
b1 5
b1 @
00
b0 3
b0 P
1*
1(
1,
0'
b101 U
b1 4
b1 D
b1 O
1!
#620000
0!
#625000
10
b1 3
b1 P
b10 9
b10 S
b1 T
1'
1.
1)
0,
0(
0*
b1 1
b1 M
b1 R
b1 2
b1 H
b110 U
1!
#630000
0!
#635000
b1 9
b1 S
b0 7
b0 ;
b0 E
b0 I
b0 Q
b1001 5
b1001 @
1'
0.
0)
b1001 3
b1001 P
b111 U
b1 6
b1 ?
b1 N
1!
#640000
0!
#645000
b1010 9
b1010 S
b1001 7
b1001 ;
b1001 E
b1001 I
b1001 Q
b1001 5
b1001 @
00
b0 3
b0 P
1.
1,
0'
b1001 4
b1001 D
b1001 O
b1000 U
1!
#650000
0!
#655000
b1 9
b1 S
b0 7
b0 ;
b0 E
b0 I
b0 Q
b101 5
b101 @
10
b101 3
b101 P
1'
0,
0.
b1001 U
b1001 6
b1001 ?
b1001 N
1!
#660000
0!
#665000
b101 7
b101 ;
b101 E
b101 I
b101 Q
b1111111111111110 T
b100 5
b100 @
b0 3
b0 P
1&
1-
b100 9
b100 S
1/
1,
0'
b101 4
b101 D
b101 O
b1010 U
1!
#670000
0!
#675000
b0 5
b0 @
b0 7
b0 ;
b0 E
b0 I
b0 Q
b1 T
00
1*
1%
0&
b1 9
b1 S
0/
0,
0-
b1011 U
b100 4
b100 D
b100 O
0#
1!
#680000
0!
#685000
b100 5
b100 @
10
b100 3
b100 P
b11 9
b11 S
b10 7
b10 ;
b10 E
b10 I
b10 Q
1'
1.
1)
0%
0*
b10 2
b10 H
b1100 U
1!
#690000
0!
